Metadata-Version: 2.1
Name: c0mrade2
Version: 0.1.0
Summary: My first Python library
Home-page: UNKNOWN
Author: c0mrade
License: MIT
Platform: UNKNOWN
